chars/__init__.py
chars/core.py
charscope-0.1.0.dist-info/licenses/LICENSE
charscope-0.1.0.dist-info/METADATA
charscope-0.1.0.dist-info/WHEEL
charscope-0.1.0.dist-info/top_level.txt
charscope-0.1.0.dist-info/RECORD
