Metadata-Version: 2.4
Name: charscope
Version: 0.1.0
Summary: Character analysis and visualization tool for ASCII and UTF-8 text.
Home-page: https://github.com/yourname/CharScope
Author: Eden Simamora
Author-email: Eden Simamora <aeden6877@gmail.com>
License: MIT
Project-URL: Homepage, https://github.com/yourname/CharScope
Requires-Python: >=3.7
License-File: LICENSE
Requires-Dist: numpy
Requires-Dist: matplotlib
Requires-Dist: colorama
Requires-Dist: pyfiglet
Dynamic: author
Dynamic: home-page
Dynamic: license-file
Dynamic: requires-python
